laplacian_pyramid_blend/__init__.py
laplacian_pyramid_blend/laplacian_pyramid_blend.py
laplacian_pyramid_blend-0.0.1.dist-info/METADATA
laplacian_pyramid_blend-0.0.1.dist-info/WHEEL
laplacian_pyramid_blend-0.0.1.dist-info/top_level.txt
laplacian_pyramid_blend-0.0.1.dist-info/RECORD
