Metadata-Version: 2.1
Name: laplacian-pyramid-blend
Version: 0.0.1
Summary: laplacian-pyramid-blend
Home-page: https://github.com/jinwonkim93/laplacian-pyramid-blend
Author: Jinwon Kim
Author-email: code.eric22@gmail.com
License: MIT
Keywords: laplacian-pyramid-blend,image
Platform: UNKNOWN
Requires-Dist: opencv-python
Requires-Dist: numpy
